nonebot_plugin_fortnite/__init__.py
nonebot_plugin_fortnite/config.py
nonebot_plugin_fortnite/pve.py
nonebot_plugin_fortnite/resources/LuckiestGuy.woff
nonebot_plugin_fortnite/resources/burbankbigregular-black.woff2
nonebot_plugin_fortnite/resources/stats_bg.png
nonebot_plugin_fortnite/shop.py
nonebot_plugin_fortnite/stats.py
nonebot_plugin_fortnite/utils.py
nonebot_plugin_fortnite-0.6.7.dist-info/WHEEL
nonebot_plugin_fortnite-0.6.7.dist-info/METADATA
nonebot_plugin_fortnite-0.6.7.dist-info/RECORD
