Metadata-Version: 2.3
Name: nonebot-plugin-fortnite
Version: 0.6.7
Summary: 堡垒之夜插件
Keywords: fortnite,nonebot,nonebot2
Author: fllesser
Author-email: fllesser <fllessive@gmail.com>
Requires-Dist: pillow>=11.2.1
Requires-Dist: aiofiles>=25.1.0
Requires-Dist: httpx>=0.28.1,<1.0.0
Requires-Dist: nonebot2>=2.4.3,<3.0.0
Requires-Dist: fortnite-api[speed]>=3.3.0,<4.0.0
Requires-Dist: nonebot-plugin-alconna>=0.59.4,<1.0.0
Requires-Dist: nonebot-plugin-apscheduler>=0.5.0,<1.0.0
Requires-Dist: nonebot-plugin-htmlrender>=0.6.7
Requires-Dist: nonebot-plugin-localstore>=0.7.4,<1.0.0
Requires-Dist: nonebot-plugin-uninfo>=0.10.1,<1.0.0
Requires-Python: >=3.10
Project-URL: Homepage, https://github.com/fllesser/nonebot-plugin-fortnite
Project-URL: Issues, https://github.com/fllesser/nonebot-plugin-fortnite/issues
Project-URL: Repository, https://github.com/fllesser/nonebot-plugin-fortnite.git
